COPYING
MANIFEST.in
README.rst
bootstrap.py
buildout.cfg
setup.py
xbob/__init__.py
xbob.fingervein.egg-info/PKG-INFO
xbob.fingervein.egg-info/SOURCES.txt
xbob.fingervein.egg-info/dependency_links.txt
xbob.fingervein.egg-info/entry_points.txt
xbob.fingervein.egg-info/namespace_packages.txt
xbob.fingervein.egg-info/requires.txt
xbob.fingervein.egg-info/top_level.txt
xbob/fingervein/__init__.py
xbob/fingervein/utils.py
xbob/fingervein/configurations/__init__.py
xbob/fingervein/configurations/tools.py
xbob/fingervein/configurations/databases/__init__.py
xbob/fingervein/configurations/databases/utfvp.py
xbob/fingervein/configurations/databases/vera.py
xbob/fingervein/configurations/features/__init__.py
xbob/fingervein/configurations/features/maximum_curvature.py
xbob/fingervein/configurations/grid/__init__.py
xbob/fingervein/configurations/grid/demanding.py
xbob/fingervein/configurations/grid/gbu.py
xbob/fingervein/configurations/grid/gpu.py
xbob/fingervein/configurations/grid/gpu2.py
xbob/fingervein/configurations/grid/gpu3.py
xbob/fingervein/configurations/grid/grid.py
xbob/fingervein/configurations/grid/large.py
xbob/fingervein/configurations/grid/local.py
xbob/fingervein/configurations/grid/small.py
xbob/fingervein/configurations/grid/very_demanding.py
xbob/fingervein/configurations/preprocessing/__init__.py
xbob/fingervein/configurations/preprocessing/finger_crop_hq.py
xbob/fingervein/configurations/preprocessing/finger_crop_hq_with_heq.py
xbob/fingervein/configurations/preprocessing/finger_crop_lq.py
xbob/fingervein/configurations/preprocessing/finger_crop_lq_with_heq.py
xbob/fingervein/features/MaximumCurvature.py
xbob/fingervein/features/__init__.py
xbob/fingervein/preprocessing/FingerCrop.py
xbob/fingervein/preprocessing/__init__.py
xbob/fingervein/script/__init__.py
xbob/fingervein/script/scores2spoofingfile.py
xbob/fingervein/tests/__init__.py
xbob/fingervein/tests/test.py
xbob/fingervein/tools/MiuraMatch.py
xbob/fingervein/tools/__init__.py