Metadata-Version: 1.1
Name: xbob.fingervein
Version: 1.0.0
Summary: Fingervein recognition based on Bob and the facereclib
Home-page: http://gitlab.idiap.ch/pedro.tome/xbob.fingervein
Author: Pedro Tome
Author-email: pedro.tome@idiap.ch
License: GPLv3
Keywords: fingervein,bob,xbob,facereclib
Platform: UNKNOWN
Classifier: Development Status :: 4 - Beta
Classifier: Intended Audience :: Developers
Classifier: License :: OSI Approved :: GNU General Public License v3 (GPLv3)
Classifier: Natural Language :: English
Classifier: Programming Language :: Python
Classifier: Topic :: Scientific/Engineering :: Artificial Intelligence
